datasette_homepage_table/__init__.py
datasette_homepage_table-0.2.dist-info/LICENSE
datasette_homepage_table-0.2.dist-info/METADATA
datasette_homepage_table-0.2.dist-info/WHEEL
datasette_homepage_table-0.2.dist-info/entry_points.txt
datasette_homepage_table-0.2.dist-info/top_level.txt
datasette_homepage_table-0.2.dist-info/RECORD
