Metadata-Version: 2.1
Name: datasette-homepage-table
Version: 0.2
Summary: Show a specific Datasette table on the homepage
Author: Simon Willison
License: Apache-2.0
Project-URL: Homepage, https://github.com/datasette/datasette-homepage-table
Project-URL: Changelog, https://github.com/datasette/datasette-homepage-table/releases
Project-URL: Issues, https://github.com/datasette/datasette-homepage-table/issues
Project-URL: CI, https://github.com/datasette/datasette-homepage-table/actions
Classifier: Framework :: Datasette
Classifier: License :: OSI Approved :: Apache Software License
Requires-Python: >=3.8
License-File: LICENSE
Requires-Dist: datasette
Provides-Extra: test
Requires-Dist: pytest ; extra == 'test'
Requires-Dist: pytest-asyncio ; extra == 'test'
Requires-Dist: datasette-test ; extra == 'test'
